chromedriver_manager/__init__.py
chromedriver_manager/module/__init__.py
chromedriver_manager/module/manager.py
chromedriver_manager/module/config/__init__.py
chromedriver_manager/module/config/logger.py
chromedriver_manager/module/config/settings.py
chromedriver_manager/module/core/__init__.py
chromedriver_manager/module/core/utils.py
chromedriver_version_manager-1.0.0.dist-info/METADATA
chromedriver_version_manager-1.0.0.dist-info/WHEEL
chromedriver_version_manager-1.0.0.dist-info/top_level.txt
chromedriver_version_manager-1.0.0.dist-info/RECORD
