Metadata-Version: 2.4
Name: chromedriver-version-manager
Version: 1.0.0
Summary: Chromedriver Version Manager
Requires-Python: >=3.10
Requires-Dist: requests>=2.32.5
